applm_models/__init__.py
applm_models/base.py
applm_models/cohere.py
applm_models/dbrx.py
applm_models/deepseek.py
applm_models/deepseek_v2.py
applm_models/gemma.py
applm_models/gemma2.py
applm_models/gpt2.py
applm_models/gpt_bigcode.py
applm_models/gpt_neox.py
applm_models/internlm2.py
applm_models/llama.py
applm_models/minicpm.py
applm_models/mixtral.py
applm_models/olmo.py
applm_models/openelm.py
applm_models/phi.py
applm_models/phi3.py
applm_models/phi3small.py
applm_models/phimoe.py
applm_models/phixtral.py
applm_models/plamo.py
applm_models/qwen.py
applm_models/qwen2.py
applm_models/qwen2_moe.py
applm_models/recurrent_gemma.py
applm_models/stablelm.py
applm_models/starcoder2.py
applm_models/su_rope.py
applm_models/switch_layers.py
applm_models-0.0.34.dist-info/LICENSE
applm_models-0.0.34.dist-info/METADATA
applm_models-0.0.34.dist-info/WHEEL
applm_models-0.0.34.dist-info/top_level.txt
applm_models-0.0.34.dist-info/RECORD
