Metadata-Version: 2.1
Name: applm-models
Version: 0.0.34
Summary: Language Model Modules for appLM on Apple Silicon
Author: Jonathan Dobson
Project-URL: Homepage, https://github.com/Jonathan-Dobson/applm-models
Project-URL: Issues, https://github.com/Jonathan-Dobson/applm-models/issues
Classifier: Programming Language :: Python :: 3
Classifier: License :: OSI Approved :: MIT License
Classifier: Operating System :: MacOS :: MacOS X
Requires-Python: >=3.8
License-File: LICENSE
